virt_s3/__init__.py
virt_s3/extras.py
virt_s3/fs.py
virt_s3/main.py
virt_s3/s3.py
virt_s3/utils.py
virt_s3-0.1.5.dist-info/LICENSE
virt_s3-0.1.5.dist-info/METADATA
virt_s3-0.1.5.dist-info/WHEEL
virt_s3-0.1.5.dist-info/RECORD
