Metadata-Version: 2.3
Name: virt-s3
Version: 0.1.5
Summary: A Virtualitics S3 Utility Library with Local File System Mirror.
Author: Virtualitics Engineering
Author-email: engineering@virtualitics.com
Requires-Python: >=3.11
Classifier: License :: OSI Approved :: MIT License
Classifier: Operating System :: MacOS :: MacOS X
Classifier: Operating System :: POSIX :: Linux
Classifier: Programming Language :: Python :: 3
Classifier: Programming Language :: Python :: 3.11
Classifier: Programming Language :: Python :: 3.12
Classifier: Programming Language :: Python :: 3.13
Provides-Extra: dataframe
Provides-Extra: docs
Provides-Extra: image
Provides-Extra: s3
Provides-Extra: test
Requires-Dist: boto3 (>=1.34.51,<2.0.0) ; extra == "s3"
Requires-Dist: numpy (>=1.26.4) ; extra == "dataframe" or extra == "image"
Requires-Dist: pandas (>=2.2.1,<3.0.0) ; extra == "dataframe"
Requires-Dist: pillow (>=10.2.0) ; extra == "image"
Requires-Dist: pyarrow (>=14.0.2) ; extra == "dataframe"
Requires-Dist: pytest (>=7.4.3,<8.0.0) ; extra == "test"
Requires-Dist: python_dotenv (>=1.0.1,<2.0.0) ; extra == "test"
Requires-Dist: sphinx (>=7.3.7,<8.0.0) ; extra == "docs"
Requires-Dist: sphinx-autodoc-typehints (>=2.1.1) ; extra == "docs"
Requires-Dist: sphinx-markdown-builder (>=0.6.6) ; extra == "docs"
